marsrover/__init__.py
marsrover/marsrover.py
marsrover-1.1.1.dist-info/LICENSE
marsrover-1.1.1.dist-info/METADATA
marsrover-1.1.1.dist-info/WHEEL
marsrover-1.1.1.dist-info/entry_points.txt
marsrover-1.1.1.dist-info/top_level.txt
marsrover-1.1.1.dist-info/RECORD
