Metadata-Version: 2.1
Name: marsrover
Version: 1.1.1
Summary: Let's go grow potatoes on Mars!
Home-page: https://becky2sawyer.github.io/mars-rover
Author: pysatellite
Author-email: pysatellite@gmail.com
License: GNU General Public License (GPL)
Project-URL: Bug Tracker, https://github.com/becky2sawyer/mars-rover/issues
Platform: macOS
Classifier: Programming Language :: Python :: 3
Classifier: License :: OSI Approved :: GNU General Public License (GPL)
Classifier: Operating System :: OS Independent
Requires-Python: >=3.6
License-File: LICENSE
